tglite
