Metadata-Version: 2.1
Name: tglite
Version: 0.0.4
Summary: Temporal GNN Lightweight Framework
Author-email: Yufeng Wang <yufengwang05@gmail.com>, Charith Mendis <charithm@illinois.edu>
Maintainer-email: Wanyu Zhao <wanyu2@illinois.edu>
License:                                  Apache License
Project-URL: homepage, https://github.com/ADAPT-uiuc/tglite
Project-URL: documentation, https://readthedocs.org
Project-URL: repository, https://github.com/ADAPT-uiuc/tglite
Project-URL: issues, https://github.com/me/ADAPT-uiuc/tglite/issues
Keywords: machine learning,TGNN
Classifier: Development Status :: 3 - Alpha
Classifier: Intended Audience :: Developers
Classifier: Intended Audience :: Science/Research
Classifier: License :: OSI Approved :: Apache Software License
Classifier: Operating System :: POSIX :: Linux
Classifier: Programming Language :: Python :: 3
Classifier: Programming Language :: Python :: 3.7
Classifier: Programming Language :: Python :: 3.8
Classifier: Programming Language :: Python :: 3.9
Classifier: Programming Language :: Python :: 3.10
Requires-Python: <3.11,>=3.7
Provides-Extra: dev
Provides-Extra: test
Provides-Extra: docs
License-File: LICENSE
